{
    "Space Brothers Blu ray Ayumu Watanabe": {
        "from": 99.98,
        "to": 26.99,
        "saving": 72.99,
        "link": "https://www.amazon.com/Space-Brothers-Blu-ray-Ayumu-Watanabe/dp/B081KQ2NTR"
    },
    "Zero Hour Crisis Anniversary Omnibus": {
        "from": 150.0,
        "to": 77.99,
        "saving": 72.01,
        "link": "https://www.amazon.com/Zero-Hour-Crisis-Anniversary-Omnibus/dp/1401294367"
    },
    "Zero Hour Expeditionary Force Book": {
        "from": 44.99,
        "to": 0.0,
        "saving": 44.99,
        "link": "https://www.amazon.com/Zero-Hour-Expeditionary-Force-Book/dp/B078RVTVQQ"
    },
    "Routing Switching Official Guide Library": {
        "from": 119.99,
        "to": 75.99,
        "saving": 44.0,
        "link": "https://www.amazon.com/Routing-Switching-Official-Guide-Library/dp/1587144921"
    },
    "Coleman North Adult Mummy Sleeping": {
        "from": 69.99,
        "to": 34.97,
        "saving": 35.02,
        "link": "https://www.amazon.com/Coleman-North-Adult-Mummy-Sleeping/dp/B0009PUSO4"
    },
    "K 2882 0 Verticyl Rectangle Undercounter Bathroom": {
        "from": 171.75,
        "to": 137.39,
        "saving": 34.36,
        "link": "https://www.amazon.com/K-2882-0-Verticyl-Rectangle-Undercounter-Bathroom/dp/B002UYSP5Q"
    },
    "SteelSeries Arctis Illuminated Headset Headphone": {
        "from": 99.99,
        "to": 74.5,
        "saving": 25.49,
        "link": "https://www.amazon.com/SteelSeries-Arctis-Illuminated-Headset-Headphone/dp/B07FZW37YS"
    },
    "Levis Womens Skinny Little Secret": {
        "from": 59.5,
        "to": 34.27,
        "saving": 25.23,
        "link": "https://www.amazon.com/Levis-Womens-Skinny-Little-Secret/dp/B072DV4X8M"
    },
    "Patient Zero Ledger Novels Book": {
        "from": 25.17,
        "to": 0.0,
        "saving": 25.17,
        "link": "https://www.amazon.com/Patient-Zero-Ledger-Novels-Book/dp/B00464E2MI"
    },
    "Diagnostic Classification Developmental Disorders Childhood": {
        "from": 69.99,
        "to": 45.49,
        "saving": 24.5,
        "link": "https://www.amazon.com/Diagnostic-Classification-Developmental-Disorders-Childhood/dp/193855857X"
    },
    "Celebrity Pink Jeans Infinite Stretch": {
        "from": 44.0,
        "to": 19.99,
        "saving": 24.01,
        "link": "https://www.amazon.com/Celebrity-Pink-Jeans-Infinite-Stretch/dp/B01LY455GY"
    },
    "Levis Womens Skinny Jeans Story": {
        "from": 59.5,
        "to": 35.7,
        "saving": 23.8,
        "link": "https://www.amazon.com/Levis-Womens-Skinny-Jeans-Story/dp/B071DMSPMG"
    },
    "Zero Limits Secret Hawaiian System": {
        "from": 20.99,
        "to": 0.0,
        "saving": 20.99,
        "link": "https://www.amazon.com/Zero-Limits-Secret-Hawaiian-System/dp/B000TD15OS"
    },
    "Generation Zero Xbox One Standard": {
        "from": 39.99,
        "to": 19.99,
        "saving": 20.0,
        "link": "https://www.amazon.com/Generation-Zero-Xbox-One-Standard/dp/B07M8STXZ8"
    },
    "Hawaii Five Eighth Alex OLoughlin": {
        "from": 49.99,
        "to": 31.07,
        "saving": 18.92,
        "link": "https://www.amazon.com/Hawaii-Five-Eighth-Alex-OLoughlin/dp/B07D58XP3Z"
    },
    "Hawaii Five Season Alex OLoughlin": {
        "from": 21.99,
        "to": 14.66,
        "saving": 7.33,
        "link": "https://www.amazon.com/Hawaii-Five-Season-Alex-OLoughlin/dp/B00ZUL9LJK"
    },
    "Japanese Zero Techniques Students Professionals": {
        "from": 32.95,
        "to": 18.52,
        "saving": 14.43,
        "link": "https://www.amazon.com/Japanese-Zero-Techniques-Students-Professionals/dp/0976998122"
    },
    "130 Properties 3 5 Years": {
        "from": 34.95,
        "to": 21.57,
        "saving": 13.38,
        "link": "https://www.amazon.com/130-Properties-3-5-Years/dp/1742169678"
    },
    "Zero One Notes Startups Future ebook": {
        "from": 28.0,
        "to": 14.99,
        "saving": 13.01,
        "link": "https://www.amazon.com/Zero-One-Notes-Startups-Future-ebook/dp/B00J6YBOFQ"
    },
    "Clothes Newborn Outfits Infant Headband": {
        "from": 26.99,
        "to": 13.98,
        "saving": 13.01,
        "link": "https://www.amazon.com/Clothes-Newborn-Outfits-Infant-Headband/dp/B07VTTLZNL"
    },
    "TOPDC Jumper Cables Gauge Booster": {
        "from": 69.99,
        "to": 59.99,
        "saving": 10.0,
        "link": "https://www.amazon.com/TOPDC-Jumper-Cables-Gauge-Booster/dp/B07N2J2W8G"
    },
    "Zero Covert ops Suspense Warriors Thrillers ebook": {
        "from": 15.99,
        "to": 7.99,
        "saving": 8.0,
        "link": "https://www.amazon.com/Zero-Covert-ops-Suspense-Warriors-Thrillers-ebook/dp/B01DMYLKPE"
    },
    "Sales Acceleration Formula Technology Inbound": {
        "from": 25.0,
        "to": 17.76,
        "saving": 7.24,
        "link": "https://www.amazon.com/Sales-Acceleration-Formula-Technology-Inbound/dp/1119047072"
    },
    "Zero Skulls Book Sam Crescent ebook": {
        "from": 11.99,
        "to": 4.99,
        "saving": 7.0,
        "link": "https://www.amazon.com/Zero-Skulls-Book-Sam-Crescent-ebook/dp/B00KGDTVOW"
    },
    "Handfasting Knights Ware Book ebook": {
        "from": 7.99,
        "to": 0.99,
        "saving": 7.0,
        "link": "https://www.amazon.com/Handfasting-Knights-Ware-Book-ebook/dp/B018IKT1TO"
    },
    "Dungeons Dragons Spellbook Cards Accessory": {
        "from": 24.99,
        "to": 18.0,
        "saving": 6.99,
        "link": "https://www.amazon.com/Dungeons-Dragons-Spellbook-Cards-Accessory/dp/0786966726"
    },
    "SteelSeries Casque Gamer Arctis Blanc 2019": {
        "from": 100.96,
        "to": 94.53,
        "saving": 6.43,
        "link": "https://www.amazon.com/SteelSeries-Casque-Gamer-Arctis-Blanc-2019/dp/B07GFWMF2Z"
    },
    "ZeroWater Pitcher Quality BPA Free Certified": {
        "from": 39.99,
        "to": 34.5,
        "saving": 5.49,
        "link": "https://www.amazon.com/ZeroWater-Pitcher-Quality-BPA-Free-Certified/dp/B003QXM3U8"
    },
    "Zero Biography Dangerous Charles Seife": {
        "from": 18.0,
        "to": 11.88,
        "saving": 6.12,
        "link": "https://www.amazon.com/Zero-Biography-Dangerous-Charles-Seife/dp/0140296476"
    },
    "Power Zero Revised Updated Retirement": {
        "from": 20.0,
        "to": 13.99,
        "saving": 6.01,
        "link": "https://www.amazon.com/Power-Zero-Revised-Updated-Retirement/dp/1984823078"
    },
    "Elkrry Tapered 0 3Months Off White Melange": {
        "from": 23.99,
        "to": 17.99,
        "saving": 6.0,
        "link": "https://www.amazon.com/Elkrry-Tapered-0-3Months-Off-White-Melange/dp/B07SQCYG8T"
    },
    "Silk Vol Life Times Cindy": {
        "from": 19.99,
        "to": 14.13,
        "saving": 5.86,
        "link": "https://www.amazon.com/Silk-Vol-Life-Times-Cindy/dp/0785197044"
    },
    "Hawaii Five 12th Final Season": {
        "from": 16.99,
        "to": 11.94,
        "saving": 5.05,
        "link": "https://www.amazon.com/Hawaii-Five-12th-Final-Season/dp/B001JAHQGG"
    },
    "Zero Waste Home Ultimate Simplifying": {
        "from": 18.0,
        "to": 13.08,
        "saving": 4.92,
        "link": "https://www.amazon.com/Zero-Waste-Home-Ultimate-Simplifying/dp/1451697686"
    },
    "Countdown Zero Day Stuxnet Digital": {
        "from": 17.0,
        "to": 12.15,
        "saving": 4.85,
        "link": "https://www.amazon.com/Countdown-Zero-Day-Stuxnet-Digital/dp/0770436196"
    },
    "Zero Belly Smoothies Pounds Healthy": {
        "from": 15.95,
        "to": 11.88,
        "saving": 4.07,
        "link": "https://www.amazon.com/Zero-Belly-Smoothies-Pounds-Healthy/dp/0399178449"
    },
    "Gerber Girls 4 Pack Cloudy Months": {
        "from": 19.99,
        "to": 15.99,
        "saving": 4.0,
        "link": "https://www.amazon.com/Gerber-Girls-4-Pack-Cloudy-Months/dp/B07GFTTYMW"
    },
    "Angels Death Episode 0 Vol 2": {
        "from": 13.0,
        "to": 9.2,
        "saving": 3.8,
        "link": "https://www.amazon.com/Angels-Death-Episode-0-Vol-2/dp/1975303989"
    },
    "Epic Zero Books 1 3 Collection": {
        "from": 19.99,
        "to": 16.23,
        "saving": 3.76,
        "link": "https://www.amazon.com/Epic-Zero-Books-1-3-Collection/dp/0998412902"
    },
    "Tommee Tippee Closer Soother Pacifier": {
        "from": 11.49,
        "to": 9.59,
        "saving": 1.9,
        "link": "https://www.amazon.com/Tommee-Tippee-Closer-Soother-Pacifier/dp/B07SBKX3CN"
    },
    "Gerber Girls 4 Pack Clouds Months": {
        "from": 16.99,
        "to": 13.59,
        "saving": 3.4,
        "link": "https://www.amazon.com/Gerber-Girls-4-Pack-Clouds-Months/dp/B07GG593DL"
    },
    "Gerber Baby Boys 4 Pack Months": {
        "from": 16.99,
        "to": 13.59,
        "saving": 3.4,
        "link": "https://www.amazon.com/Gerber-Baby-Boys-4-Pack-Months/dp/B07GFTV583"
    },
    "Gerber 8 Pack Short Sleeve Onesies Bodysuit": {
        "from": 15.99,
        "to": 12.79,
        "saving": 3.2,
        "link": "https://www.amazon.com/Gerber-8-Pack-Short-Sleeve-Onesies-Bodysuit/dp/B07GFPVS2M"
    },
    "Gerber Organic Long Sleeve Onesies Bodysuit": {
        "from": 15.99,
        "to": 12.79,
        "saving": 3.2,
        "link": "https://www.amazon.com/Gerber-Organic-Long-Sleeve-Onesies-Bodysuit/dp/B07GDSRZ1B"
    },
    "Gerber Long Sleeve Mitten Cuff Onesies Bodysuit": {
        "from": 17.99,
        "to": 14.88,
        "saving": 3.11,
        "link": "https://www.amazon.com/Gerber-Long-Sleeve-Mitten-Cuff-Onesies-Bodysuit/dp/B07GFNVLS2"
    },
    "Gerber Organic Short Sleeve Onesies Bodysuit": {
        "from": 12.99,
        "to": 9.99,
        "saving": 3.0,
        "link": "https://www.amazon.com/Gerber-Organic-Short-Sleeve-Onesies-Bodysuit/dp/B07GDS658J"
    },
    "EDENS ZERO Vol Hiro Mashima ebook": {
        "from": 10.99,
        "to": 7.99,
        "saving": 3.0,
        "link": "https://www.amazon.com/EDENS-ZERO-Vol-Hiro-Mashima-ebook/dp/B07JWJL39V"
    },
    "Zero Sugar Diet Flatten Cravings": {
        "from": 28.0,
        "to": 25.2,
        "saving": 2.8,
        "link": "https://www.amazon.com/Zero-Sugar-Diet-Flatten-Cravings/dp/0345547985"
    },
    "Gerber Girls 4 Pack Stripe Months": {
        "from": 12.99,
        "to": 10.39,
        "saving": 2.6,
        "link": "https://www.amazon.com/Gerber-Girls-4-Pack-Stripe-Months/dp/B07GFXY5YY"
    },
    "Gerber 2 Pack Sleep Happy Months": {
        "from": 11.99,
        "to": 9.59,
        "saving": 2.4,
        "link": "https://www.amazon.com/Gerber-2-Pack-Sleep-Happy-Months/dp/B07CS2BYDZ"
    },
    "Gerber Girls 2 Pack Sleep Months": {
        "from": 11.99,
        "to": 9.59,
        "saving": 2.4,
        "link": "https://www.amazon.com/Gerber-Girls-2-Pack-Sleep-Months/dp/B07CS2QHSM"
    },
    "Simple Joys Carters 2 Pack Hoodies": {
        "from": 17.58,
        "to": 15.3,
        "saving": 2.28,
        "link": "https://www.amazon.com/Simple-Joys-Carters-2-Pack-Hoodies/dp/B079616C43"
    },
    "Epic Zero Books 4 6 Collection": {
        "from": 23.99,
        "to": 21.86,
        "saving": 2.13,
        "link": "https://www.amazon.com/Epic-Zero-Books-4-6-Collection/dp/1734061200"
    },
    "Amazon Essentials 2 Pack Microfleece Stripe": {
        "from": 15.64,
        "to": 13.6,
        "saving": 2.04,
        "link": "https://www.amazon.com/Amazon-Essentials-2-Pack-Microfleece-Stripe/dp/B07Q42PRQG"
    },
    "Zero Stone Murdoc Jern Book ebook": {
        "from": 9.99,
        "to": 7.99,
        "saving": 2.0,
        "link": "https://www.amazon.com/Zero-Stone-Murdoc-Jern-Book-ebook/dp/B016LP32PM"
    },
    "Epeius Baby Girls Eyelet Ruffle Newborn": {
        "from": 17.9,
        "to": 15.9,
        "saving": 2.0,
        "link": "https://www.amazon.com/Epeius-Baby-Girls-Eyelet-Ruffle-Newborn/dp/B07TKVRDF1"
    },
    "Angels Death Episode 0 Vol": {
        "from": 13.0,
        "to": 11.14,
        "saving": 1.86,
        "link": "https://www.amazon.com/Angels-Death-Episode-0-Vol/dp/1975359518"
    },
    "101 Ways Go Zero Waste": {
        "from": 17.95,
        "to": 16.16,
        "saving": 1.79,
        "link": "https://www.amazon.com/101-Ways-Go-Zero-Waste/dp/1682683311"
    },
    "Force Vol 0 Warzones": {
        "from": 16.99,
        "to": 15.22,
        "saving": 1.77,
        "link": "https://www.amazon.com/Force-Vol-0-Warzones/dp/078519861X"
    },
    "One Minute Zero Robert Mitchum": {
        "from": 12.99,
        "to": 11.59,
        "saving": 1.4,
        "link": "https://www.amazon.com/One-Minute-Zero-Robert-Mitchum/dp/B005DIA0IQ"
    },
    "Philips Avent Soothie Pacifier Months": {
        "from": 4.49,
        "to": 3.19,
        "saving": 1.3,
        "link": "https://www.amazon.com/Philips-Avent-Soothie-Pacifier-Months/dp/B0045I6IAY"
    },
    "ZeroWater Tumbler Replacement Filters BPA Free": {
        "from": 12.99,
        "to": 11.78,
        "saving": 1.21,
        "link": "https://www.amazon.com/ZeroWater-Tumbler-Replacement-Filters-BPA-Free/dp/B00C1TLKNE"
    },
    "Luvable Friends Unisex Newborn Ballet": {
        "from": 9.99,
        "to": 8.94,
        "saving": 1.05,
        "link": "https://www.amazon.com/Luvable-Friends-Unisex-Newborn-Ballet/dp/B00X23Z6QK"
    },
    "Newborn Toddler Walkers Bootie Infant": {
        "from": 10.98,
        "to": 9.98,
        "saving": 1.0,
        "link": "https://www.amazon.com/Newborn-Toddler-Walkers-Bootie-Infant/dp/B07H3VD828"
    },
    "Zero Martin Caiden ebook": {
        "from": 4.99,
        "to": 4.49,
        "saving": 0.5,
        "link": "https://www.amazon.com/Zero-Martin-Caiden-ebook/dp/B06XGL1T5Z"
    },
    "%E5%BE%9E0%E5%88%B01 %E6%89%93%E9%96%8B%E4%B8%96%E7%95%8C%E9%81%8B%E4%BD%9C%E7%9A%84%E6%9C%AA%E7%9F%A5%E7%A5%95%E5%AF%86%EF%BC%8C%E5%9C%A8%E6%84%8F%E6%83%B3%E4%B8%8D%E5%88%B0%E4%B9%8B%E8%99%95%E7%99%BC%E7%8F%BE%E5%83%B9%E5%80%BC %E5%BD%BC%E5%BE%97%C2%B7%E6%8F%90%E7%88%BE Peter Thiel ebook": {
        "from": 8.4,
        "to": 8.12,
        "saving": 0.28,
        "link": "https://www.amazon.com/%E5%BE%9E0%E5%88%B01-%E6%89%93%E9%96%8B%E4%B8%96%E7%95%8C%E9%81%8B%E4%BD%9C%E7%9A%84%E6%9C%AA%E7%9F%A5%E7%A5%95%E5%AF%86%EF%BC%8C%E5%9C%A8%E6%84%8F%E6%83%B3%E4%B8%8D%E5%88%B0%E4%B9%8B%E8%99%95%E7%99%BC%E7%8F%BE%E5%83%B9%E5%80%BC-%E5%BD%BC%E5%BE%97%C2%B7%E6%8F%90%E7%88%BE-Peter-Thiel-ebook/dp/B07PBJHXXK"
    },
    "Zero Day John Puller Book ebook": {
        "from": 10.0,
        "to": 9.99,
        "saving": 0.01,
        "link": "https://www.amazon.com/Zero-Day-John-Puller-Book-ebook/dp/B004TI5N38"
    }
}